dalec_caldav/__init__.py
dalec_caldav/apps.py
dalec_caldav/proxy.py
tests/__init__.py
tests/apps.py
tests/models.py
tests/settings.py
tests/tests.py
tests/urls.py
dalec_caldav-0.2.0.dist-info/AUTHORS
dalec_caldav-0.2.0.dist-info/LICENSE
dalec_caldav-0.2.0.dist-info/METADATA
dalec_caldav-0.2.0.dist-info/WHEEL
dalec_caldav-0.2.0.dist-info/top_level.txt
dalec_caldav-0.2.0.dist-info/RECORD
